mkdocs_branchcustomization_plugin/__init__.py
mkdocs_branchcustomization_plugin/_version.py
mkdocs_branchcustomization_plugin/plugin.py
mkdocs_branchcustomization_plugin-0.1.3.dist-info/METADATA
mkdocs_branchcustomization_plugin-0.1.3.dist-info/WHEEL
mkdocs_branchcustomization_plugin-0.1.3.dist-info/entry_points.txt
mkdocs_branchcustomization_plugin-0.1.3.dist-info/top_level.txt
mkdocs_branchcustomization_plugin-0.1.3.dist-info/RECORD
