Metadata-Version: 2.1
Name: mkdocs-branchcustomization-plugin
Version: 0.1.3
Summary: Update mkdocs configuration based on the git branch
Home-page: https://github.com/effigies/mkdocs-branchcustomization-plugin
Author: Christopher J. Markiewicz
Author-email: markiewicz@stanford.edu
Maintainer: Christopher J. Markiewicz
Maintainer-email: markiewicz@stanford.edu
License: MIT License
Platform: OS Independent
Classifier: Development Status :: 3 - Alpha
Classifier: License :: OSI Approved :: MIT License
Classifier: Operating System :: OS Independent
Classifier: Programming Language :: Python
Classifier: Programming Language :: Python :: 3.5
Classifier: Programming Language :: Python :: 3.6
Classifier: Programming Language :: Python :: 3.7
Classifier: Programming Language :: Python :: 3.8
Provides: mkdocs_branchcustomization_plugin
Requires-Python: >=3.6
Requires-Dist: mkdocs
Requires-Dist: gitpython
